osintgpt/__init__.py
osintgpt/config/__init__.py
osintgpt/config/gpt_api.py
osintgpt/databases/__init__.py
osintgpt/databases/sql_manager.py
osintgpt/embedding/__init__.py
osintgpt/embedding/embedding_generator.py
osintgpt/embedding/openai_embeddings.py
osintgpt/embeddings/__init__.py
osintgpt/embeddings/openai_embeddings.py
osintgpt/exceptions/__init__.py
osintgpt/exceptions/errors.py
osintgpt/gpt/__init__.py
osintgpt/gpt/openai_gpt.py
osintgpt/llms/__init__.py
osintgpt/llms/openai_gpt.py
osintgpt/prompts/__init__.py
osintgpt/prompts/summarizing.py
osintgpt/semantic_operations/__init__.py
osintgpt/semantic_operations/operations.py
osintgpt/utils/__init__.py
osintgpt/vector_store/__init__.py
osintgpt/vector_store/base.py
osintgpt/vector_store/pinecone.py
osintgpt/vector_store/pinecone_client.py
osintgpt/vector_store/qdrant.py
osintgpt/vector_store/vector_pinecone.py
osintgpt/vector_store/vector_qdrant.py
osintgpt/vectore_stores/__init__.py
osintgpt/vectore_stores/qdrant.py
osintgpt-0.1.27.dist-info/METADATA
osintgpt-0.1.27.dist-info/WHEEL
osintgpt-0.1.27.dist-info/top_level.txt
osintgpt-0.1.27.dist-info/RECORD
