Metadata-Version: 2.1
Name: osintgpt
Version: 0.1.27
Summary: A Python OSINT tool using Large Language Models
Home-page: https://github.com/estebanpdl/osintgpt
Author: Esteban Ponce de Leon
Classifier: Development Status :: 3 - Alpha
Classifier: Programming Language :: Python
Classifier: Programming Language :: Python :: 3.7
Classifier: Programming Language :: Python :: 3.8
Classifier: Programming Language :: Python :: 3.9
Classifier: Programming Language :: Python :: 3.10
Classifier: Programming Language :: Python :: 3.11
Classifier: Operating System :: OS Independent
Classifier: Intended Audience :: Science/Research
Classifier: Intended Audience :: Education
Classifier: Intended Audience :: Information Technology
Classifier: Intended Audience :: Developers
Classifier: Topic :: Scientific/Engineering :: Artificial Intelligence
Classifier: Topic :: Scientific/Engineering :: Information Analysis
Classifier: Topic :: Text Processing
Classifier: Topic :: Text Processing :: General
Classifier: Topic :: Text Processing :: Indexing
Classifier: Topic :: Utilities
Requires-Python: >=3.7
Requires-Dist: openai (==0.28)
Requires-Dist: pandas
Requires-Dist: python-dotenv
Requires-Dist: qdrant-client
Requires-Dist: scipy
Requires-Dist: tiktoken
